classtools.py
setup.py
classtools.egg-info/PKG-INFO
classtools.egg-info/SOURCES.txt
classtools.egg-info/dependency_links.txt
classtools.egg-info/top_level.txt