Metadata-Version: 1.1
Name: classtools
Version: 0.1
Summary: A few class utilities the stdlib is missing.
Home-page: https://github.com/eevee/classtools
Author: Eevee
Author-email: eevee.classtools@veekun.com
License: MIT
Keywords: class development
Platform: UNKNOWN
Classifier: Development Status :: 2 - Pre-Alpha
Classifier: Intended Audience :: Developers
Classifier: License :: OSI Approved :: ISC License (ISCL)
Classifier: Programming Language :: Python :: 2
Classifier: Programming Language :: Python :: 2.6
Classifier: Programming Language :: Python :: 2.7
Classifier: Programming Language :: Python :: 3
Classifier: Programming Language :: Python :: 3.2
Classifier: Programming Language :: Python :: 3.3
Classifier: Programming Language :: Python :: 3.4
